LICENSE
README.md
setup.py
assertions/__init__.py
assertions/assertions.py
assertions/constants.py
assertions/operators.py
assertions/utils.py
assertions/validators.py
assertions/formatters/__init__.py
assertions/formatters/assertions.py
assertions/formatters/validators.py
assertions/solutions/__init__.py
assertions/solutions/common.py
assertions/solutions/models.py
assertions/solutions/response.py
pytest_assertions.egg-info/PKG-INFO
pytest_assertions.egg-info/SOURCES.txt
pytest_assertions.egg-info/dependency_links.txt
pytest_assertions.egg-info/requires.txt
pytest_assertions.egg-info/top_level.txt