Metadata-Version: 2.1
Name: pytest-assertions
Version: 0.2.1
Summary: Pytest Assertions
Home-page: https://github.com/Nikita-Filonov/assertions
Author: Nikita Filonov
Author-email: filonov.nikitkaa@gmail.com
License: UNKNOWN
Platform: UNKNOWN
License-File: LICENSE
